{
	"cloakoffnpc": {
		"params": {
			"NPC object name": {
				"type": "string",
				"default": "*?*",
				"doc": []
			},
			"account_id": {
				"type": "number",
				"default": "*?*",
				"doc": []
			}
		},
		"signatures": [
			[
				"NPC object name"
			],
			[
				"NPC object name",
				"account_id"
			]
		],
		"doc": [
			"These commands are used to apply the cloaking effect on npcs\n",
			"this is a visual effect only and it does NOT stop the player\n",
			"from interacting with the npc.\n",
			"\n",
			"If an account_id is specified then the effect will only display to the given id,\n",
			"otherwise it's displayed to the entire npc area.\n"
		],
		"return": "unknown",
		"deprecated": false
	}
}