{"cleararray":{"params":[{"array name[<first value to alter>]":"int","value":"int","number of values to set":"int"}],"paramDoc":{"array name[<first value to alter>]":"Missing Documentation","value":"Missing Documentation","number of values to set":"Missing Documentation"},"doc":["This command will change many array values at the same time to the same","value.","setarray(.@array, 100, 200, 300, 400, 500, 600);","// This will make all 6 values 0","cleararray(.@array[0], 0, 6);","// This will make array element 0 change to 245","cleararray(.@array[0], 245, 1);","// This is equivalent to the above","cleararray(.@array, 245, 1);","// This will make elements 1 and 2 change to 345","cleararray(.@array[1], 345, 2);","See 'setarray'."]}}