{"countitem2":{"params":[{"item name":"string","identify":"int","refine":"int","attribute":"int","card1":"int","card2":"int","card3":"int","card4":"int"}],"paramDoc":{"item name":"Missing Documentation","identify":"Missing Documentation","refine":"Missing Documentation","attribute":"Missing Documentation","card1":"Missing Documentation","card2":"Missing Documentation","card3":"Missing Documentation","card4":"Missing Documentation"},"doc":["Expanded version of countitem() function, used for created/carded/forged","items.","This function will return the number of items for the specified item ID","and other parameters that the invoking character has in the inventory.","Check getitem2() to understand the arguments of the function."]}}